spline/__init__.py
spline/application.py
spline/matrix.py
spline/pipeline.py
spline/validation.py
spline/version.py
spline/components/__init__.py
spline/components/ansible.py
spline/components/bash.py
spline/components/config.py
spline/components/docker.py
spline/components/hooks.py
spline/components/packer.py
spline/components/script.py
spline/components/stage.py
spline/components/tasks.py
spline/components/templates/ansible.sh.j2
spline/components/templates/docker-container.sh.j2
spline/components/templates/docker-image.sh.j2
spline/components/templates/packer-image.sh.j2
spline/components/templates/python-script.sh.j2
spline/tools/__init__.py
spline/tools/adapter.py
spline/tools/condition.py
spline/tools/decorators.py
spline/tools/event.py
spline/tools/filters.py
spline/tools/loader.py
spline/tools/logger.py
spline/tools/memfiles.py
spline/tools/query.py
spline/tools/stream.py
spline/tools/table.py
spline/tools/version.py
spline/tools/loc/__init__.py
spline/tools/loc/application.py
spline/tools/loc/templates/spline-loc.yml.j2
spline/tools/report/__init__.py
spline/tools/report/collector.py
spline/tools/report/generator.py
spline/tools/report/templates/report.html.j2
spline-1.11.data/scripts/spline
spline-1.11.data/scripts/spline-loc
spline-1.11.dist-info/DESCRIPTION.rst
spline-1.11.dist-info/METADATA
spline-1.11.dist-info/RECORD
spline-1.11.dist-info/WHEEL
spline-1.11.dist-info/metadata.json
spline-1.11.dist-info/top_level.txt
