Metadata-Version: 2.0
Name: spline
Version: 1.11
Summary: (s)hell oriented (p)ipe(line) tool for ci/cd
Home-page: https://github.com/Nachtfeuer/pipeline
Author: Thomas Lehmann
Author-email: thomas.lehmann.private@gmail.com
License: MIT
Keywords: pipeline tool ci/cd bash docker packer ansible python
Platform: UNKNOWN
Classifier: Development Status :: 5 - Production/Stable
Classifier: Programming Language :: Python :: 2.7
Classifier: Programming Language :: Python :: 3.4
Classifier: Programming Language :: Python :: 3.5
Classifier: Programming Language :: Python :: 3.6
Classifier: Programming Language :: Python :: Implementation :: PyPy
Classifier: Intended Audience :: Developers
Classifier: License :: OSI Approved :: MIT License
Classifier: Operating System :: Unix
Classifier: Environment :: Console
Classifier: Topic :: Utilities
Requires-Dist: click
Requires-Dist: jinja2
Requires-Dist: pyaml
Requires-Dist: schema
